[
{"id":"bo3-1","fecha":"2021-01-13","tipo":"EGRESO","descripcion":"Luis Augier","ancho":"1.1","alto":"1.65"},
{"id":"bo3-2","fecha":"2021-01-20","tipo":"EGRESO","descripcion":"Tomas Mierez","ancho":"1.7","alto":"1.55"},
{"id":"bo3-3","fecha":"2021-01-22","tipo":"EGRESO","descripcion":"Ezequiel","ancho":"1.52","alto":"1.6"},
{"id":"bo3-4","fecha":"2021-02-02","tipo":"EGRESO","descripcion":"Lucas","ancho":"1.76","alto":"1.76"},
{"id":"bo3-5","fecha":"2021-02-12","tipo":"INGRESO","descripcion":"ROLLTECH","ancho":"1.83","alto":"30"},
{"id":"bo3-6","fecha":"2021-03-03","tipo":"EGRESO","descripcion":"Arturo","ancho":"1.7","alto":"1.6"},
{"id":"bo3-7","fecha":"2021-03-16","tipo":"EGRESO","descripcion":"Luis San Vicente","ancho":"1.7","alto":"2.1"},
{"id":"bo3-8","fecha":"2021-03-16","tipo":"EGRESO","descripcion":"Luis San Vicente","ancho":"1.7","alto":"2.1"},
{"id":"bo3-9","fecha":"2021-03-16","tipo":"EGRESO","descripcion":"Luis San Vicente","ancho":"1.7","alto":"2.1"},
{"id":"bo3-10","fecha":"2021-04-08","tipo":"EGRESO","descripcion":"Karina - Fcia Bettel","ancho":"0.88","alto":"2.55"},
{"id":"bo3-11","fecha":"2021-04-16","tipo":"INGRESO","descripcion":"ALUCA","ancho":"1.83","alto":"30"},
{"id":"bo3-12","fecha":"2021-05-05","tipo":"EGRESO","descripcion":"Dario Alvez","ancho":"1.7","alto":"2.5"},
{"id":"bo3-13","fecha":"2021-05-05","tipo":"EGRESO","descripcion":"Dario Alvez","ancho":"1.7","alto":"1.9"},
{"id":"bo3-14","fecha":"2021-05-11","tipo":"EGRESO","descripcion":"Fiama (Animal W)","ancho":"1.539","alto":"2.57"},
{"id":"bo3-15","fecha":"2021-05-11","tipo":"EGRESO","descripcion":"Fiama (Animal W)","ancho":"1.539","alto":"2.57"},
{"id":"bo3-16","fecha":"2021-05-19","tipo":"EGRESO","descripcion":"Maria Laura Melgarejo","ancho":"0.6","alto":"0.9"},
{"id":"bo3-17","fecha":"2021-05-19","tipo":"EGRESO","descripcion":"NILU","ancho":"1.515","alto":"2.44"},
{"id":"bo3-18","fecha":"2021-05-19","tipo":"EGRESO","descripcion":"NILU","ancho":"1.515","alto":"2.44"},
{"id":"bo3-19","fecha":"2021-05-21","tipo":"EGRESO","descripcion":"Graciela Lang","ancho":"1.7","alto":"1.9"},
{"id":"bo3-20","fecha":"2021-05-21","tipo":"EGRESO","descripcion":"Graciela Lang","ancho":"1.7","alto":"1.9"},
{"id":"bo3-21","fecha":"2021-06-07","tipo":"EGRESO","descripcion":"Karla","ancho":"1.6","alto":"1.8"},
{"id":"bo3-22","fecha":"2021-06-11","tipo":"EGRESO","descripcion":"Monica Seewald","ancho":"1.1","alto":"2.7"},
{"id":"bo3-23","fecha":"2021-08-02","tipo":"EGRESO","descripcion":"Graciela Nuñez","ancho":"1.58","alto":"0.84"},
{"id":"bo3-24","fecha":"2021-08-02","tipo":"EGRESO","descripcion":"Graciela Nuñez","ancho":"1.58","alto":"0.84"},
{"id":"bo3-25","fecha":"2021-08-09","tipo":"EGRESO","descripcion":"Ramiro Acuña","ancho":"1.6","alto":"2.45"},
{"id":"bo3-26","fecha":"2021-09-02","tipo":"INGRESO","descripcion":"ALUCA","ancho":"1.83","alto":"30"},
{"id":"bo3-27","fecha":"2021-09-22","tipo":"EGRESO","descripcion":"Maria Escalada","ancho":"1.67","alto":"1.6"},
{"id":"bo3-28","fecha":"2021-10-04","tipo":"EGRESO","descripcion":"Julieta Aranda","ancho":"1.68","alto":"1.6"},
{"id":"bo3-29","fecha":"2021-10-04","tipo":"EGRESO","descripcion":"Julieta Aranda","ancho":"1.68","alto":"1.6"},
{"id":"bo3-30","fecha":"2021-10-04","tipo":"EGRESO","descripcion":"Julieta Aranda","ancho":"1.68","alto":"1.6"},
{"id":"bo3-31","fecha":"2021-10-04","tipo":"EGRESO","descripcion":"Julieta Aranda","ancho":"1.68","alto":"1.6"},
{"id":"bo3-32","fecha":"2021-11-12","tipo":"INGRESO","descripcion":"TODO ROLLER","ancho":"1.83","alto":"30"},
{"id":"bo3-33","fecha":"2021-11-30","tipo":"EGRESO","descripcion":"Hospital","ancho":"1.75","alto":"2.34"},
{"id":"bo3-34","fecha":"2021-11-30","tipo":"EGRESO","descripcion":"Hospital","ancho":"1.75","alto":"2.34"},
{"id":"bo3-35","fecha":"2021-12-09","tipo":"EGRESO","descripcion":"PJ Cuerpo Medico Forense SV","ancho":"1.759","alto":"3.46"},
{"id":"bo3-36","fecha":"2022-02-03","tipo":"INGRESO","descripcion":"ALUCA","ancho":"1.83","alto":"35"},
{"id":"bo3-37","fecha":"2022-02-17","tipo":"EGRESO","descripcion":"Luis Schwegler","ancho":"1.7","alto":"1.7"},
{"id":"bo3-38","fecha":"2022-03-15","tipo":"EGRESO","descripcion":"Daniel Brignocoli","ancho":"1.83","alto":"1.7"},
{"id":"bo3-39","fecha":"2022-03-15","tipo":"EGRESO","descripcion":"Daniel Brignocoli","ancho":"1.83","alto":"1.7"},
{"id":"bo3-40","fecha":"2022-03-15","tipo":"EGRESO","descripcion":"Ana Maria (Duomo)","ancho":"1.75","alto":"1.7"},
{"id":"bo3-41","fecha":"2022-03-16","tipo":"INGRESO","descripcion":"PRINTEMPS","ancho":"1.83","alto":"30"},
{"id":"bo3-42","fecha":"2022-03-30","tipo":"EGRESO","descripcion":"Mariela","ancho":"1.02","alto":"1.9"},
{"id":"bo3-43","fecha":"2022-03-30","tipo":"EGRESO","descripcion":"Mariela","ancho":"1.79","alto":"1.9"},
{"id":"bo3-44","fecha":"2022-03-30","tipo":"EGRESO","descripcion":"Mariela","ancho":"0.8","alto":"1.9"},
{"id":"bo3-45","fecha":"2022-04-12","tipo":"EGRESO","descripcion":"Camara laboral P2 - Expte 438","ancho":"1.635","alto":"1.5"},
{"id":"bo3-46","fecha":"2022-04-19","tipo":"EGRESO","descripcion":"Def. Montecarlo Expte 835-22","ancho":"1.61","alto":"2.5"},
{"id":"bo3-47","fecha":"2022-04-19","tipo":"EGRESO","descripcion":"Def. Montecarlo Expte 835-22","ancho":"1.61","alto":"2.5"},
{"id":"bo3-48","fecha":"2022-04-19","tipo":"EGRESO","descripcion":"Def. Montecarlo Expte 835-22","ancho":"1.71","alto":"2.1"},
{"id":"bo3-49","fecha":"2022-04-29","tipo":"INGRESO","descripcion":"PRINTEMPS","ancho":"1.83","alto":"30"},
{"id":"bo3-50","fecha":"2022-05-03","tipo":"EGRESO","descripcion":"Carlos Beigbeder","ancho":"1.7","alto":"1.56"},
{"id":"bo3-51","fecha":"2022-05-03","tipo":"EGRESO","descripcion":"Carlos Beigbeder","ancho":"1.7","alto":"1.56"},
{"id":"bo3-52","fecha":"2022-05-13","tipo":"INGRESO","descripcion":"EURODEC","ancho":"1.83","alto":"30"},
{"id":"bo3-53","fecha":"2022-05-19","tipo":"EGRESO","descripcion":"Def. Montecarlo expte 835 (2)","ancho":"1.71","alto":"2.5"}
]
