[
{"id":"bo6-1","fecha":"2021-01-27","tipo":"EGRESO","descripcion":"Julia Gonzalez","ancho":"0.9","alto":"1.5"},
{"id":"bo6-2","fecha":"2021-02-11","tipo":"EGRESO","descripcion":"DUOMO HELADOS","ancho":"1.676","alto":"5.4"},
{"id":"bo6-3","fecha":"2021-02-11","tipo":"EGRESO","descripcion":"DUOMO HELADOS","ancho":"1.676","alto":"5.4"},
{"id":"bo6-4","fecha":"2021-02-11","tipo":"EGRESO","descripcion":"DUOMO HELADOS","ancho":"1.357","alto":"5.4"},
{"id":"bo6-5","fecha":"2021-02-23","tipo":"EGRESO","descripcion":"Cesar P.Rico","ancho":"1.34","alto":"3"},
{"id":"bo6-6","fecha":"2021-02-23","tipo":"EGRESO","descripcion":"Cesar P.Rico","ancho":"1.66","alto":"3"},
{"id":"bo6-7","fecha":"2021-02-23","tipo":"EGRESO","descripcion":"Cesar P.Rico","ancho":"1.66","alto":"3"},
{"id":"bo6-8","fecha":"2021-02-23","tipo":"EGRESO","descripcion":"Cesar P.Rico","ancho":"1.68","alto":"3"},
{"id":"bo6-9","fecha":"2021-02-23","tipo":"EGRESO","descripcion":"Cesar P.Rico","ancho":"1.74","alto":"3"},
{"id":"bo6-10","fecha":"2021-02-25","tipo":"EGRESO","descripcion":"Luciana Muzlumian","ancho":"1.6","alto":"2.5"},
{"id":"bo6-11","fecha":"2021-02-25","tipo":"EGRESO","descripcion":"Luciana Muzlumian","ancho":"1.6","alto":"2.5"},
{"id":"bo6-12","fecha":"2021-02-25","tipo":"EGRESO","descripcion":"Paola Sanabria","ancho":"0.747","alto":"2.3"},
{"id":"bo6-13","fecha":"2021-02-25","tipo":"EGRESO","descripcion":"Paola Sanabria","ancho":"1.627","alto":"1.65"},
{"id":"bo6-14","fecha":"2021-02-25","tipo":"EGRESO","descripcion":"Paola Sanabria","ancho":"1.572","alto":"1.65"},
{"id":"bo6-15","fecha":"2021-02-26","tipo":"EGRESO","descripcion":"Susana Duran","ancho":"0.81","alto":"1"},
{"id":"bo6-16","fecha":"2021-02-26","tipo":"EGRESO","descripcion":"Susana Duran","ancho":"0.81","alto":"1"},
{"id":"bo6-17","fecha":"2021-02-26","tipo":"EGRESO","descripcion":"Susana Duran","ancho":"0.54","alto":"1"},
{"id":"bo6-18","fecha":"2021-02-26","tipo":"EGRESO","descripcion":"Noelia","ancho":"1.4","alto":"1.6"},
{"id":"bo6-19","fecha":"2021-03-02","tipo":"EGRESO","descripcion":"Pablo Sode","ancho":"1.5","alto":"2.25"},
{"id":"bo6-20","fecha":"2021-03-10","tipo":"INGRESO","descripcion":"ROLLTECH","ancho":"1.83","alto":"30"},
{"id":"bo6-21","fecha":"2021-03-10","tipo":"EGRESO","descripcion":"Adrian","ancho":"0.94","alto":"2"},
{"id":"bo6-22","fecha":"2021-03-10","tipo":"EGRESO","descripcion":"Adrian","ancho":"0.94","alto":"2"},
{"id":"bo6-23","fecha":"2021-03-10","tipo":"EGRESO","descripcion":"Adrian","ancho":"1.64","alto":"2"},
{"id":"bo6-24","fecha":"2021-03-20","tipo":"EGRESO","descripcion":"Solis Claudio","ancho":"1.7","alto":"1.5"},
{"id":"bo6-25","fecha":"2021-04-06","tipo":"EGRESO","descripcion":"Silvana","ancho":"1.6","alto":"1.5"},
{"id":"bo6-26","fecha":"2021-04-14","tipo":"EGRESO","descripcion":"Mauro","ancho":"1.54","alto":"1.8"},
{"id":"bo6-27","fecha":"2021-04-19","tipo":"EGRESO","descripcion":"Angel Cardozo","ancho":"1.74","alto":"2.2"},
{"id":"bo6-28","fecha":"2021-04-19","tipo":"EGRESO","descripcion":"Angel Cardozo","ancho":"1.74","alto":"2.2"},
{"id":"bo6-29","fecha":"2021-04-19","tipo":"EGRESO","descripcion":"Angel Cardozo","ancho":"1.71","alto":"2.2"},
{"id":"bo6-30","fecha":"2021-04-20","tipo":"EGRESO","descripcion":"DUOMO HELADOS","ancho":"1.47","alto":"3.4"},
{"id":"bo6-31","fecha":"2021-04-20","tipo":"EGRESO","descripcion":"DUOMO HELADOS","ancho":"1.47","alto":"3.4"},
{"id":"bo6-32","fecha":"2021-04-20","tipo":"EGRESO","descripcion":"DUOMO HELADOS","ancho":"1.47","alto":"3.4"},
{"id":"bo6-33","fecha":"2021-04-21","tipo":"EGRESO","descripcion":"Edi Castro","ancho":"1.6","alto":"1.5"},
{"id":"bo6-34","fecha":"2021-04-27","tipo":"EGRESO","descripcion":"Celia","ancho":"1.03","alto":"1.9"},
{"id":"bo6-35","fecha":"2021-04-27","tipo":"EGRESO","descripcion":"Celia","ancho":"1.03","alto":"1.9"},
{"id":"bo6-36","fecha":"2021-05-03","tipo":"EGRESO","descripcion":"Evelin Lovera","ancho":"1.64","alto":"1.8"},
{"id":"bo6-37","fecha":"2021-05-11","tipo":"EGRESO","descripcion":"Gema Rotella","ancho":"1.3","alto":"1.5"},
{"id":"bo6-38","fecha":"2021-05-11","tipo":"EGRESO","descripcion":"Guadalupe","ancho":"1.54","alto":"1.45"},
{"id":"bo6-39","fecha":"2021-05-13","tipo":"EGRESO","descripcion":"ANIMAL WORD","ancho":"1.765","alto":"2.56"},
{"id":"bo6-40","fecha":"2021-05-13","tipo":"EGRESO","descripcion":"ANIMAL WORD","ancho":"1.795","alto":"2.56"},
{"id":"bo6-41","fecha":"2021-05-14","tipo":"EGRESO","descripcion":"CAROLINA MELGAREJO","ancho":"1.07","alto":"1.64"},
{"id":"bo6-42","fecha":"2021-05-17","tipo":"EGRESO","descripcion":"ANAHI SOTO","ancho":"0.94","alto":"2.75"},
{"id":"bo6-43","fecha":"2021-05-17","tipo":"EGRESO","descripcion":"ANAHI SOTO","ancho":"0.94","alto":"2.75"},
{"id":"bo6-44","fecha":"2021-05-18","tipo":"EGRESO","descripcion":"EVE ESCALADA","ancho":"1.29","alto":"3"},
{"id":"bo6-45","fecha":"2021-05-19","tipo":"EGRESO","descripcion":"Paola Sanabria","ancho":"1.626","alto":"1.7"},
{"id":"bo6-46","fecha":"2021-05-19","tipo":"EGRESO","descripcion":"Paola Sanabria","ancho":"1.618","alto":"1.7"},
{"id":"bo6-47","fecha":"2021-05-19","tipo":"EGRESO","descripcion":"Maria Laura Melgarejo","ancho":"1.4","alto":"1.45"},
{"id":"bo6-48","fecha":"2021-05-19","tipo":"EGRESO","descripcion":"Maria Laura Melgarejo","ancho":"1.4","alto":"1.45"},
{"id":"bo6-49","fecha":"2021-05-19","tipo":"EGRESO","descripcion":"Maria Laura Melgarejo","ancho":"0.6","alto":"0.9"},
{"id":"bo6-50","fecha":"2021-05-20","tipo":"EGRESO","descripcion":"DEFENSORIA","ancho":"1.05","alto":"0.76"},
{"id":"bo6-51","fecha":"2021-05-20","tipo":"EGRESO","descripcion":"DEFENSORIA","ancho":"1.05","alto":"0.76"},
{"id":"bo6-52","fecha":"2021-05-21","tipo":"INGRESO","descripcion":"ALUCA","ancho":"1.83","alto":"30"},
{"id":"bo6-53","fecha":"2021-05-28","tipo":"EGRESO","descripcion":"susana","ancho":"1.05","alto":"1.5"},
{"id":"bo6-54","fecha":"2021-05-28","tipo":"EGRESO","descripcion":"susana","ancho":"1.05","alto":"1.5"},
{"id":"bo6-55","fecha":"2021-06-03","tipo":"EGRESO","descripcion":"Paula Gorelik","ancho":"1.7","alto":"2"},
{"id":"bo6-56","fecha":"2021-06-03","tipo":"EGRESO","descripcion":"Paula Gorelik","ancho":"1.7","alto":"2.5"},
{"id":"bo6-57","fecha":"2021-06-03","tipo":"EGRESO","descripcion":"Paula Gorelik","ancho":"1.7","alto":"2.5"},
{"id":"bo6-58","fecha":"2021-06-03","tipo":"EGRESO","descripcion":"Gladys","ancho":"1.6","alto":"1.4"},
{"id":"bo6-59","fecha":"2021-06-04","tipo":"EGRESO","descripcion":"Josefina","ancho":"1.4","alto":"1.8"},
{"id":"bo6-60","fecha":"2021-06-07","tipo":"EGRESO","descripcion":"Isabel","ancho":"1.61","alto":"1.5"},
{"id":"bo6-61","fecha":"2021-06-08","tipo":"EGRESO","descripcion":"Emanuel Pellizer","ancho":"1.7","alto":"2.5"},
{"id":"bo6-62","fecha":"2021-06-30","tipo":"EGRESO","descripcion":"Natalia","ancho":"1.83","alto":"1.5"},
{"id":"bo6-63","fecha":"2021-07-01","tipo":"INGRESO","descripcion":"ALUCA","ancho":"1.83","alto":"30"},
{"id":"bo6-64","fecha":"2021-07-12","tipo":"EGRESO","descripcion":"Maria Eugenia","ancho":"1.63","alto":"1.63"},
{"id":"bo6-65","fecha":"2021-07-14","tipo":"EGRESO","descripcion":"Vladimir Glynka","ancho":"1.7","alto":"1.55"},
{"id":"bo6-66","fecha":"2021-07-27","tipo":"EGRESO","descripcion":"Vladimir Glynka","ancho":"1.65","alto":"3.1"},
{"id":"bo6-67","fecha":"2021-08-04","tipo":"EGRESO","descripcion":"Gonzalo Zapana","ancho":"0.647","alto":"1.8"},
{"id":"bo6-68","fecha":"2021-08-04","tipo":"EGRESO","descripcion":"Gonzalo Zapana","ancho":"0.65","alto":"2"},
{"id":"bo6-69","fecha":"2021-08-13","tipo":"EGRESO","descripcion":"Morales Alberto","ancho":"1.7","alto":"1.65"},
{"id":"bo6-70","fecha":"2021-08-13","tipo":"EGRESO","descripcion":"Morales Alberto","ancho":"1.7","alto":"1.65"},
{"id":"bo6-71","fecha":"2021-09-15","tipo":"EGRESO","descripcion":"Marcia","ancho":"1.722","alto":"3.15"},
{"id":"bo6-72","fecha":"2021-09-15","tipo":"EGRESO","descripcion":"Marcia","ancho":"1.665","alto":"2.6"},
{"id":"bo6-73","fecha":"2021-09-15","tipo":"EGRESO","descripcion":"Marcia","ancho":"1.69","alto":"2.6"},
{"id":"bo6-74","fecha":"2021-09-15","tipo":"EGRESO","descripcion":"Marcia","ancho":"1.69","alto":"2.6"},
{"id":"bo6-75","fecha":"2021-10-01","tipo":"EGRESO","descripcion":"Carolina Melgarejo","ancho":"1.66","alto":"1.4"},
{"id":"bo6-76","fecha":"2021-10-12","tipo":"EGRESO","descripcion":"NICOLAS SEGOVIA","ancho":"1.75","alto":"2.4"},
{"id":"bo6-77","fecha":"2021-10-18","tipo":"EGRESO","descripcion":"Luis de Leon","ancho":"0.868","alto":"1.6"},
{"id":"bo6-78","fecha":"2021-10-18","tipo":"EGRESO","descripcion":"Luis de Leon","ancho":"0.868","alto":"1.6"},
{"id":"bo6-79","fecha":"2021-11-12","tipo":"INGRESO","descripcion":"TODO ROLLER","ancho":"1.83","alto":"30"},
{"id":"bo6-80","fecha":"2021-11-24","tipo":"EGRESO","descripcion":"Pedro Puerta","ancho":"1.72","alto":"1.8"},
{"id":"bo6-81","fecha":"2021-12-20","tipo":"EGRESO","descripcion":"Ana Maria Nuñez 2","ancho":"1.788","alto":"1.74"},
{"id":"bo6-82","fecha":"2021-12-20","tipo":"EGRESO","descripcion":"Ana Maria Nuñez 2","ancho":"1.798","alto":"1.74"},
{"id":"bo6-83","fecha":"2021-12-28","tipo":"EGRESO","descripcion":"Yessica Mattos","ancho":"1.75","alto":"1.54"},
{"id":"bo6-84","fecha":"2021-12-30","tipo":"EGRESO","descripcion":"Christian Gimenez","ancho":"2.1","alto":"1.4"},
{"id":"bo6-85","fecha":"2022-01-26","tipo":"EGRESO","descripcion":"Gerardo","ancho":"1.81","alto":"3.2"},
{"id":"bo6-86","fecha":"2022-01-26","tipo":"EGRESO","descripcion":"Gerardo","ancho":"1.755","alto":"3.2"},
{"id":"bo6-87","fecha":"2022-01-26","tipo":"EGRESO","descripcion":"Gerardo","ancho":"0.875","alto":"3.2"},
{"id":"bo6-88","fecha":"2022-01-26","tipo":"EGRESO","descripcion":"Gerardo","ancho":"1.72","alto":"3.2"},
{"id":"bo6-89","fecha":"2022-01-26","tipo":"EGRESO","descripcion":"Gerardo","ancho":"0.84","alto":"3.2"},
{"id":"bo6-90","fecha":"2022-02-09","tipo":"EGRESO","descripcion":"Alfredo Ibañez","ancho":"1.73","alto":"1.53"},
{"id":"bo6-91","fecha":"2022-02-17","tipo":"EGRESO","descripcion":"Delia Gonzalez","ancho":"1.84","alto":"1.6"},
{"id":"bo6-92","fecha":"2022-02-21","tipo":"EGRESO","descripcion":"Veronica","ancho":"1.75","alto":"1.55"},
{"id":"bo6-93","fecha":"2022-02-22","tipo":"EGRESO","descripcion":"MARANDU","ancho":"1.83","alto":"2.52"},
{"id":"bo6-94","fecha":"2022-03-07","tipo":"EGRESO","descripcion":"Leticia Magaldi 2","ancho":"1.712","alto":"2.03"},
{"id":"bo6-95","fecha":"2022-03-07","tipo":"EGRESO","descripcion":"Leticia Magaldi 2","ancho":"1.43","alto":"1.5"},
{"id":"bo6-96","fecha":"2022-03-07","tipo":"EGRESO","descripcion":"Leticia Magaldi 2","ancho":"0.4","alto":"1.4"},
{"id":"bo6-97","fecha":"2022-03-14","tipo":"EGRESO","descripcion":"Pablo Zillmer","ancho":"1.85","alto":"2.26"},
{"id":"bo6-98","fecha":"2022-03-16","tipo":"INGRESO","descripcion":"PRINTEMPS","ancho":"1.83","alto":"30"},
{"id":"bo6-99","fecha":"2022-04-13","tipo":"EGRESO","descripcion":"Viviana","ancho":"1.83","alto":"1.9"},
{"id":"bo6-100","fecha":"2022-05-02","tipo":"EGRESO","descripcion":"Melina Fernandez","ancho":"1.79","alto":"2.43"},
{"id":"bo6-101","fecha":"2022-05-02","tipo":"EGRESO","descripcion":"Melina Fernandez","ancho":"1.65","alto":"2.16"},
{"id":"bo6-102","fecha":"2022-05-02","tipo":"EGRESO","descripcion":"Melina Fernandez","ancho":"1.79","alto":"1.66"},
{"id":"bo6-103","fecha":"2022-05-03","tipo":"EGRESO","descripcion":"Daniel Bresan","ancho":"1.765","alto":"2.1"},
{"id":"bo6-104","fecha":"2022-05-12","tipo":"EGRESO","descripcion":"MARISA MAREK","ancho":"0.78","alto":"2.6"},
{"id":"bo6-105","fecha":"2022-05-12","tipo":"EGRESO","descripcion":"MARISA MAREK","ancho":"0.78","alto":"2.6"},
{"id":"bo6-106","fecha":"2022-05-13","tipo":"INGRESO","descripcion":"EURODEC","ancho":"1.83","alto":"30"},
{"id":"bo6-107","fecha":"2022-06-10","tipo":"INGRESO","descripcion":"ALUCA","ancho":"1.83","alto":"30"}
]
